ebay_rest/__init__.py
ebay_rest/__main__.py
ebay_rest/a_p_i.py
ebay_rest/a_p_i_private.py
ebay_rest/date_time.py
ebay_rest/digital_signatures.py
ebay_rest/error.py
ebay_rest/multiton.py
ebay_rest/rates.py
ebay_rest/reference.py
ebay_rest/token.py
ebay_rest/api/__init__.py
ebay_rest/api/buy_browse/__init__.py
ebay_rest/api/buy_browse/api_client.py
ebay_rest/api/buy_browse/configuration.py
ebay_rest/api/buy_browse/rest.py
ebay_rest/api/buy_browse/api/__init__.py
ebay_rest/api/buy_browse/api/item_api.py
ebay_rest/api/buy_browse/api/item_summary_api.py
ebay_rest/api/buy_browse/models/__init__.py
ebay_rest/api/buy_browse/models/additional_product_identity.py
ebay_rest/api/buy_browse/models/addon_service.py
ebay_rest/api/buy_browse/models/address.py
ebay_rest/api/buy_browse/models/amount.py
ebay_rest/api/buy_browse/models/aspect.py
ebay_rest/api/buy_browse/models/aspect_distribution.py
ebay_rest/api/buy_browse/models/aspect_group.py
ebay_rest/api/buy_browse/models/aspect_value_distribution.py
ebay_rest/api/buy_browse/models/attribute_name_value.py
ebay_rest/api/buy_browse/models/authenticity_guarantee_program.py
ebay_rest/api/buy_browse/models/authenticity_verification_program.py
ebay_rest/api/buy_browse/models/auto_corrections.py
ebay_rest/api/buy_browse/models/available_coupon.py
ebay_rest/api/buy_browse/models/buying_option_distribution.py
ebay_rest/api/buy_browse/models/category.py
ebay_rest/api/buy_browse/models/category_distribution.py
ebay_rest/api/buy_browse/models/common_descriptions.py
ebay_rest/api/buy_browse/models/company_address.py
ebay_rest/api/buy_browse/models/compatibility_payload.py
ebay_rest/api/buy_browse/models/compatibility_property.py
ebay_rest/api/buy_browse/models/compatibility_response.py
ebay_rest/api/buy_browse/models/condition_descriptor.py
ebay_rest/api/buy_browse/models/condition_descriptor_value.py
ebay_rest/api/buy_browse/models/condition_distribution.py
ebay_rest/api/buy_browse/models/converted_amount.py
ebay_rest-1.1.3.dist-info/licenses/LICENSE
ebay_rest-1.1.3.dist-info/METADATA
ebay_rest-1.1.3.dist-info/WHEEL
ebay_rest-1.1.3.dist-info/top_level.txt
ebay_rest-1.1.3.dist-info/RECORD
