Metadata-Version: 2.4
Name: ebay_rest
Version: 1.1.3
Summary: Wraps the eBay REST APIs.
Author-email: Peter JOHN Matecsa <matecsaj@gmail.com>
License-Expression: MIT
Project-URL: Homepage, https://github.com/matecsaj/ebay_rest
Project-URL: Repository, https://github.com/matecsaj/ebay_rest.git
Project-URL: Issues, https://github.com/matecsaj/ebay_rest/issues
Keywords: ebay,api,rest
Classifier: Programming Language :: Python :: 3
Classifier: Programming Language :: Python :: 3 :: Only
Classifier: Programming Language :: Python :: 3.10
Classifier: Programming Language :: Python :: 3.11
Classifier: Programming Language :: Python :: 3.12
Classifier: Programming Language :: Python :: 3.13
Classifier: Programming Language :: Python :: 3.14
Classifier: Operating System :: OS Independent
Classifier: Development Status :: 5 - Production/Stable
Classifier: Intended Audience :: Developers
Classifier: Natural Language :: English
Classifier: Topic :: Internet
Requires-Python: >=3.10
License-File: LICENSE
Requires-Dist: certifi
Requires-Dist: cryptography
Requires-Dist: requests
Requires-Dist: python-dateutil
Requires-Dist: six
Requires-Dist: urllib3
Provides-Extra: complete
Requires-Dist: playwright; extra == "complete"
Provides-Extra: dev
Requires-Dist: aiofiles; extra == "dev"
Requires-Dist: aiohttp; extra == "dev"
Requires-Dist: black; extra == "dev"
Requires-Dist: bs4; extra == "dev"
Requires-Dist: build; extra == "dev"
Requires-Dist: chardet; extra == "dev"
Requires-Dist: CurrencyConverter; extra == "dev"
Requires-Dist: pipreqs; extra == "dev"
Requires-Dist: setuptools; extra == "dev"
Requires-Dist: twine; extra == "dev"
Requires-Dist: wheel; extra == "dev"
Dynamic: license-file
